{"Milestone": {"_rallyAPIMajor": "2", "_rallyAPIMinor": "0", "_ref": "https://rally1.rallydev.com/slm/webservice/v2.0/milestone/458348180488", "_refObjectUUID": "fc9d9a86-f123-4798-bf06-d8ffd37d1a57", "_objectVersion": "61", "_refObjectName": "ITOC Devops RND", "CreationDate": "2020-11-20T08:36:10.076Z", "_CreatedAt": "Nov 20", "ObjectID": 458348180488, "ObjectUUID": "fc9d9a86-f123-4798-bf06-d8ffd37d1a57", "VersionId": "61", "Subscription": {"_rallyAPIMajor": "2", "_rallyAPIMinor": "0", "_ref": "https://rally1.rallydev.com/slm/webservice/v2.0/subscription/10703512987", "_refObjectUUID": "29cfebbc-f94e-4b35-9813-24357191e28c", "_refObjectName": "Vantiv Inc - OH", "_type": "Subscription"}, "Workspace": {"_rallyAPIMajor": "2", "_rallyAPIMinor": "0", "_ref": "https://rally1.rallydev.com/slm/webservice/v2.0/workspace/10703513144", "_refObjectUUID": "fb101c1f-30ff-432f-a8d5-d5b3d56d96d5", "_refObjectName": "WorldPay/FIS Enterprise", "_type": "Workspace"}, "Description": "Another description data from post API in new line", "DisplayColor": "#848689", "FormattedID": "MI3952", "LastUpdateDate": "2020-11-26T07:05:36.587Z", "Name": "ITOC Devops RND", "Notes": "\u003Cp\u003EAnother Notes data from post API in new line\u003C/p\u003E\nAnother Notes data from post API in new line", "Recycled": false, "RevisionHistory": {"_rallyAPIMajor": "2", "_rallyAPIMinor": "0", "_ref": "https://rally1.rallydev.com/slm/webservice/v2.0/revisionhistory/458348180492", "_refObjectUUID": "8a4810e5-55e7-4950-bab3-085600cf7c30", "_type": "RevisionHistory"}, "Artifacts": {"_rallyAPIMajor": "2", "_rallyAPIMinor": "0", "_ref": "https://rally1.rallydev.com/slm/webservice/v2.0/Milestone/458348180488/Artifacts", "_type": "Artifact", "Count": 0}, "Projects": {"_rallyAPIMajor": "2", "_rallyAPIMinor": "0", "_ref": "https://rally1.rallydev.com/slm/webservice/v2.0/Milestone/458348180488/Projects", "_type": "Project", "Count": 1}, "TargetDate": "2021-01-26T05:00:00.000Z", "TargetProject": null, "TotalArtifactCount": 0, "TotalProjectCount": 1, "Errors": [], "Warnings": []}}